jps_forge/__init__.py
jps_forge/constants.py
jps_forge/forge.py
jps_forge/indexer.py
jps_forge/tools.py
jps_forge-0.3.0.dist-info/licenses/LICENSE
jps_forge-0.3.0.dist-info/METADATA
jps_forge-0.3.0.dist-info/WHEEL
jps_forge-0.3.0.dist-info/entry_points.txt
jps_forge-0.3.0.dist-info/top_level.txt
jps_forge-0.3.0.dist-info/RECORD
